regex_custom_dict/__init__.py
regex_custom_dict/regex_custom_dict.py
regex_custom_dict-0.6.dist-info/LICENSE
regex_custom_dict-0.6.dist-info/METADATA
regex_custom_dict-0.6.dist-info/WHEEL
regex_custom_dict-0.6.dist-info/top_level.txt
regex_custom_dict-0.6.dist-info/RECORD
