Metadata-Version: 2.1
Name: regex-custom-dict
Version: 0.6
Summary: UNKNOWN
Home-page: UNKNOWN
License: UNKNOWN
Platform: UNKNOWN
